{
	"info": {
		"_postman_id": "cbab598b-dc90-4041-ab1f-ca1b10364a2e",
		"name": "DA4ACAD Tutorial",
		"schema": "https://schema.getpostman.com/json/collection/v2.1.0/collection.json"
	},
	"item": [
		{
			"name": "Task 1 - Obtain an Access Token",
			"item": [
				{
					"name": "Get an Access Token",
					"event": [
						{
							"listen": "test",
							"script": {
								"id": "e7342707-f41f-45d7-896e-a668e052bbfc",
								"exec": [
									"var body = JSON.parse(responseBody);",
									"pm.environment.set(\"dasApiToken\", body[\"access_token\"]);"
								],
								"type": "text/javascript"
							}
						}
					],
					"request": {
						"method": "POST",
						"header": [
							{
								"key": "Content-Type",
								"value": "application/x-www-form-urlencoded"
							}
						],
						"body": {
							"mode": "urlencoded",
							"urlencoded": [
								{
									"key": "client_id",
									"value": "{{client_id}}",
									"type": "text"
								},
								{
									"key": "client_secret",
									"value": "{{client_secret}}",
									"type": "text"
								},
								{
									"key": "grant_type",
									"value": "client_credentials",
									"type": "text"
								},
								{
									"key": "scope",
									"value": "code:all data:write data:read bucket:create bucket:delete bucket:read",
									"type": "text"
								}
							]
						},
						"url": {
							"raw": "https://developer.api.autodesk.com/authentication/v1/authenticate",
							"protocol": "https",
							"host": [
								"developer",
								"api",
								"autodesk",
								"com"
							],
							"path": [
								"authentication",
								"v1",
								"authenticate"
							]
						},
						"description": "[See Documentation](https://forge.autodesk.com/en/docs/oauth/v2/reference/http/authenticate-POST/)"
					},
					"response": []
				}
			],
			"protocolProfileBehavior": {}
		},
		{
			"name": "Task 2 - Create a Nickname",
			"item": [
				{
					"name": "Create Nickname",
					"request": {
						"auth": {
							"type": "noauth"
						},
						"method": "PATCH",
						"header": [
							{
								"key": "Authorization",
								"value": "Bearer {{dasApiToken}}",
								"type": "text"
							},
							{
								"key": "Content-Type",
								"value": "application/json",
								"type": "text"
							}
						],
						"body": {
							"mode": "raw",
							"raw": "{\n\t\"nickname\": \"{{dasNickName}}\"\n}"
						},
						"url": {
							"raw": "https://developer.api.autodesk.com/da/us-east/v3/forgeapps/me",
							"protocol": "https",
							"host": [
								"developer",
								"api",
								"autodesk",
								"com"
							],
							"path": [
								"da",
								"us-east",
								"v3",
								"forgeapps",
								"me"
							]
						},
						"description": "[See documentation](https://forge.autodesk.com/en/docs/design-automation/v3/reference/http/forgeapps-id-PATCH/)"
					},
					"response": []
				}
			],
			"protocolProfileBehavior": {}
		},
		{
			"name": "Task 3 - Upload AppBundle",
			"item": [
				{
					"name": "Register the AppBundle",
					"event": [
						{
							"listen": "test",
							"script": {
								"id": "b7f12a27-5199-465f-978a-2291085e1d12",
								"exec": [
									"var body = JSON.parse(responseBody);",
									"pm.environment.set(\"ListLayersAppUrl\", body[\"uploadParameters\"][\"endpointURL\"]);",
									"pm.environment.set(\"ListLayersAppVersion\", body[\"version\"]);",
									"pm.environment.set(\"ListLayersAppFormDataKey\", body[\"uploadParameters\"][\"formData\"][\"key\"]);",
									"pm.environment.set(\"ListLayersAppFormDataPolicy\", body[\"uploadParameters\"][\"formData\"][\"policy\"]);",
									"pm.environment.set(\"ListLayersAppFormDataSignature\", body[\"uploadParameters\"][\"formData\"][\"x-amz-signature\"]);",
									"pm.environment.set(\"ListLayersAppFormDataCredential\", body[\"uploadParameters\"][\"formData\"][\"x-amz-credential\"]);",
									"pm.environment.set(\"ListLayersAppFormDataDate\", body[\"uploadParameters\"][\"formData\"][\"x-amz-date\"]);",
									"pm.environment.set(\"ListLayersAppFormDataToken\", body[\"uploadParameters\"][\"formData\"][\"x-amz-security-token\"]);",
									"pm.environment.set(\"ListLayersAppFormRedirect\", body[\"uploadParameters\"][\"formData\"][\"success_action_redirect\"]);"
								],
								"type": "text/javascript"
							}
						}
					],
					"request": {
						"method": "POST",
						"header": [
							{
								"key": "Authorization",
								"value": "Bearer {{dasApiToken}}",
								"type": "text"
							},
							{
								"key": "Content-Type",
								"value": "application/json",
								"type": "text"
							}
						],
						"body": {
							"mode": "raw",
							"raw": "{\n  \"id\": \"{{dasAppBundleName}}\",\n  \"engine\": \"Autodesk.AutoCAD+23\",\n  \"description\": \"List Layers AppBundle based on AutoCAD 2020\"\n}"
						},
						"url": {
							"raw": "https://developer.api.autodesk.com/da/us-east/v3/appbundles",
							"protocol": "https",
							"host": [
								"developer",
								"api",
								"autodesk",
								"com"
							],
							"path": [
								"da",
								"us-east",
								"v3",
								"appbundles"
							]
						},
						"description": "[See documentation](https://forge.autodesk.com/en/docs/design-automation/v3/reference/http/appbundles-POST/)"
					},
					"response": []
				},
				{
					"name": "Upload the AppBundle",
					"event": [
						{
							"listen": "prerequest",
							"script": {
								"id": "3d596d83-6ce2-4cd1-b702-bb5f9e83fcef",
								"exec": [
									""
								],
								"type": "text/javascript"
							}
						},
						{
							"listen": "test",
							"script": {
								"id": "fdb0a16e-f86f-483a-bc5f-4dec03012079",
								"exec": [
									"pm.environment.unset(\"ListLayersAppFormDataKey\");",
									"pm.environment.unset(\"ListLayersAppFormDataPolicy\");",
									"pm.environment.unset(\"ListLayersAppFormDataSignature\");",
									"pm.environment.unset(\"ListLayersAppFormDataCredential\");",
									"pm.environment.unset(\"ListLayersAppFormDataDate\");",
									"pm.environment.unset(\"ListLayersAppFormDataToken\");"
								],
								"type": "text/javascript"
							}
						}
					],
					"request": {
						"method": "POST",
						"header": [],
						"body": {
							"mode": "formdata",
							"formdata": [
								{
									"key": "key",
									"value": "{{ListLayersAppFormDataKey}}",
									"type": "text"
								},
								{
									"key": "content-type",
									"value": "application/octet-stream",
									"type": "text"
								},
								{
									"key": "policy",
									"value": "{{ListLayersAppFormDataPolicy}}",
									"type": "text"
								},
								{
									"key": "success_action_status",
									"value": "200",
									"type": "text"
								},
								{
									"key": "x-amz-signature",
									"value": "{{ListLayersAppFormDataSignature}}",
									"type": "text"
								},
								{
									"key": "x-amz-credential",
									"value": "{{ListLayersAppFormDataCredential}}",
									"type": "text"
								},
								{
									"key": "x-amz-algorithm",
									"value": "AWS4-HMAC-SHA256",
									"type": "text"
								},
								{
									"key": "x-amz-date",
									"value": "{{ListLayersAppFormDataDate}}",
									"type": "text"
								},
								{
									"key": "x-amz-server-side-encryption",
									"value": "AES256",
									"type": "text"
								},
								{
									"key": "x-amz-security-token",
									"value": "{{ListLayersAppFormDataToken}}",
									"type": "text"
								},
								{
									"key": "success_action_redirect",
									"value": "{{ListLayersAppFormRedirect}}",
									"type": "text"
								},
								{
									"key": "file",
									"type": "file",
									"src": []
								}
							]
						},
						"url": {
							"raw": "{{ListLayersAppUrl}}",
							"host": [
								"{{ListLayersAppUrl}}"
							]
						},
						"description": "This request to the Design Automation API uploads an AppBundle to Forge.\n\n&nbsp;\n\nBefore you send this request: \n\n  1. Download the file *ListLayers.zip* from the [*tutorial_data* folder of the repository that contained this Postman Collection](https://github.com/Autodesk-Forge/forge-tutorial-postman/tree/master/DA4ACAD/tutorial_data).\n  2. Go to the **Body** tab below.\n  3. Scroll down so that the **File** row is visible.\n  4. Click **Select** and pick *ListLayers.zip*, which you downloaded in step 1."
					},
					"response": []
				},
				{
					"name": "Create an Alias for the AppBundle",
					"event": [
						{
							"listen": "test",
							"script": {
								"id": "aa4a32f1-5424-47e4-9e1b-a6a6f9973df6",
								"exec": [
									"var body = JSON.parse(responseBody);",
									"pm.environment.set(\"dasAppBundleAlias\", body[\"id\"]);"
								],
								"type": "text/javascript"
							}
						}
					],
					"request": {
						"method": "POST",
						"header": [
							{
								"key": "",
								"value": "",
								"disabled": true
							},
							{
								"key": "Authorization",
								"value": "Bearer {{dasApiToken}}"
							},
							{
								"key": "Content-Type",
								"value": "application/json"
							}
						],
						"body": {
							"mode": "raw",
							"raw": "{\r\n  \"version\": {{ListLayersAppVersion}},\r\n  \"id\": \"my_working_version\"\r\n}"
						},
						"url": {
							"raw": "https://developer.api.autodesk.com/da/us-east/v3/appbundles/{{dasAppBundleName}}/aliases",
							"protocol": "https",
							"host": [
								"developer",
								"api",
								"autodesk",
								"com"
							],
							"path": [
								"da",
								"us-east",
								"v3",
								"appbundles",
								"{{dasAppBundleName}}",
								"aliases"
							]
						},
						"description": "[See documentation](https://forge.autodesk.com/en/docs/design-automation/v3/reference/http/appbundles-id-aliases-POST/)"
					},
					"response": []
				}
			],
			"protocolProfileBehavior": {}
		},
		{
			"name": "Task 4 - Publish an Activity",
			"item": [
				{
					"name": "Create a New Activity",
					"event": [
						{
							"listen": "test",
							"script": {
								"id": "1c276a3e-1707-41b5-9643-685d1364fb5c",
								"exec": [
									""
								],
								"type": "text/javascript"
							}
						}
					],
					"request": {
						"method": "POST",
						"header": [
							{
								"key": "Content-Type",
								"value": "application/json"
							},
							{
								"key": "Authorization",
								"value": "Bearer {{dasApiToken}}"
							}
						],
						"body": {
							"mode": "raw",
							"raw": "{\n  \"id\": \"{{dasActivityName}}\",\n  \"commandLine\": [\n    \"$(engine.path)\\\\accoreconsole.exe /i \\\"$(args[InputDwg].path)\\\" /al \\\"$(appbundles[{{dasAppBundleName}}].path)\\\" /s \\\"$(settings[script].path)\\\"\"\n  ],\n  \"parameters\": {\n    \"InputDwg\": {\n      \"zip\": false,\n      \"ondemand\": false,\n      \"verb\": \"get\",\n      \"description\": \"Input drawing file\",\n      \"localName\": \"Input.dwg\"\n    },\n    \"result\": {\n      \"zip\": false,\n      \"ondemand\": false,\n      \"verb\": \"put\",\n      \"description\": \"Results\",\n      \"required\": true,\n      \"localName\": \"layers.txt\"\n    }\n  },\n  \"engine\": \"Autodesk.AutoCAD+22\",\n  \"appbundles\": [\n    \"{{dasNickName}}.{{dasAppBundleName}}+{{dasAppBundleAlias}}\"\n  ],\n  \"settings\": {\n    \"script\": \"(command \\\"LISTLAYERS\\\")\\n\"\n  },\n  \"description\": \"Extracts layer names from an input drawing file and saves them to a text file\"\n}"
						},
						"url": {
							"raw": "https://developer.api.autodesk.com/da/us-east/v3/activities",
							"protocol": "https",
							"host": [
								"developer",
								"api",
								"autodesk",
								"com"
							],
							"path": [
								"da",
								"us-east",
								"v3",
								"activities"
							]
						},
						"description": "[See documentation](https://forge.autodesk.com/en/docs/design-automation/v3/reference/http/activities-POST/)"
					},
					"response": []
				},
				{
					"name": "Create an Alias for the Activity",
					"event": [
						{
							"listen": "test",
							"script": {
								"id": "50db8d74-d9d5-4460-b0b2-cf1ff1f7b4ea",
								"exec": [
									"var body = JSON.parse(responseBody);",
									"pm.environment.set(\"dasActivityAlias\", body[\"id\"]);"
								],
								"type": "text/javascript"
							}
						}
					],
					"request": {
						"method": "POST",
						"header": [
							{
								"key": "Content-Type",
								"value": "application/json"
							},
							{
								"key": "Authorization",
								"value": "Bearer {{dasApiToken}} "
							}
						],
						"body": {
							"mode": "raw",
							"raw": "{\r\n    \"id\": \"my_current_version\",\r\n    \"version\": 1\r\n}"
						},
						"url": {
							"raw": "https://developer.api.autodesk.com/da/us-east/v3/activities/{{dasActivityName}}/aliases",
							"protocol": "https",
							"host": [
								"developer",
								"api",
								"autodesk",
								"com"
							],
							"path": [
								"da",
								"us-east",
								"v3",
								"activities",
								"{{dasActivityName}}",
								"aliases"
							]
						},
						"description": "[See documentation](https://forge.autodesk.com/en/docs/design-automation/v3/reference/http/activities-id-aliases-POST/)"
					},
					"response": []
				}
			],
			"event": [
				{
					"listen": "prerequest",
					"script": {
						"id": "f6171070-6a9d-405c-afd1-8283d1bd5e19",
						"type": "text/javascript",
						"exec": [
							""
						]
					}
				},
				{
					"listen": "test",
					"script": {
						"id": "9aeaa3f0-7e03-4f56-bd5c-26f94e2ed01b",
						"type": "text/javascript",
						"exec": [
							""
						]
					}
				}
			],
			"protocolProfileBehavior": {}
		},
		{
			"name": "Task 5 - Prepare Cloud Storage",
			"item": [
				{
					"name": "Create a Bucket",
					"event": [
						{
							"listen": "test",
							"script": {
								"id": "d798b06c-cc34-452a-8e8b-77dda52f4bad",
								"exec": [
									"var body = JSON.parse(responseBody);",
									"pm.environment.set(\"ossBucketKey\", body[\"bucketKey\"]);"
								],
								"type": "text/javascript"
							}
						}
					],
					"request": {
						"method": "POST",
						"header": [
							{
								"key": "Content-Type",
								"value": "application/json"
							},
							{
								"key": "Authorization",
								"value": "Bearer {{dasApiToken}}"
							}
						],
						"body": {
							"mode": "raw",
							"raw": "{\n\t\"bucketKey\": \"{{ossBucketKey}}\",\n\t\"access\": \"full\",\n\t\"policyKey\": \"transient\"\n}\n"
						},
						"url": {
							"raw": "https://developer.api.autodesk.com/oss/v2/buckets",
							"protocol": "https",
							"host": [
								"developer",
								"api",
								"autodesk",
								"com"
							],
							"path": [
								"oss",
								"v2",
								"buckets"
							]
						},
						"description": "[See documentation](https://forge.autodesk.com/en/docs/data/v2/reference/http/buckets-POST/)"
					},
					"response": []
				},
				{
					"name": "Upload Input File to OSS",
					"event": [
						{
							"listen": "test",
							"script": {
								"id": "d0343ad2-94f0-4b57-bf5c-f89285ef0b01",
								"exec": [
									"var body = JSON.parse(responseBody);",
									"pm.environment.set(\"ossDwgFileObjectKey\", body[\"objectKey\"]);"
								],
								"type": "text/javascript"
							}
						}
					],
					"request": {
						"method": "PUT",
						"header": [
							{
								"key": "Authorization",
								"value": "Bearer {{dasApiToken}}"
							}
						],
						"body": {
							"mode": "file",
							"file": {}
						},
						"url": {
							"raw": "https://developer.api.autodesk.com/oss/v2/buckets/{{ossBucketKey}}/objects/{{ossDwgFileObjectKey}}",
							"protocol": "https",
							"host": [
								"developer",
								"api",
								"autodesk",
								"com"
							],
							"path": [
								"oss",
								"v2",
								"buckets",
								"{{ossBucketKey}}",
								"objects",
								"{{ossDwgFileObjectKey}}"
							]
						},
						"description": "[See documentation](https://forge.autodesk.com/en/docs/data/v2/reference/http/buckets-:bucketKey-objects-:objectName-PUT/)"
					},
					"response": []
				},
				{
					"name": "Get Temporary Download URL",
					"event": [
						{
							"listen": "test",
							"script": {
								"id": "ccd64087-feb2-4212-a0b2-200bb31de560",
								"exec": [
									"var body = JSON.parse(responseBody);",
									"pm.environment.set(\"ossDwgFileSignedUrl\", body[\"signedUrl\"]);",
									""
								],
								"type": "text/javascript"
							}
						}
					],
					"request": {
						"method": "POST",
						"header": [
							{
								"key": "Content-Type",
								"value": "application/json"
							},
							{
								"key": "Authorization",
								"value": "Bearer {{dasApiToken}}"
							}
						],
						"body": {
							"mode": "raw",
							"raw": "{}\n"
						},
						"url": {
							"raw": "https://developer.api.autodesk.com/oss/v2/buckets/{{ossBucketKey}}/objects/{{ossDwgFileObjectKey}}/signed",
							"protocol": "https",
							"host": [
								"developer",
								"api",
								"autodesk",
								"com"
							],
							"path": [
								"oss",
								"v2",
								"buckets",
								"{{ossBucketKey}}",
								"objects",
								"{{ossDwgFileObjectKey}}",
								"signed"
							]
						},
						"description": "[See documentation](https://forge.autodesk.com/en/docs/data/v2/reference/http/buckets-:bucketKey-objects-:objectName-signed-POST/)"
					},
					"response": []
				},
				{
					"name": "Get Temporary Upload URL",
					"event": [
						{
							"listen": "prerequest",
							"script": {
								"id": "fc6baf87-e384-4d56-9698-6dfc5b588350",
								"exec": [
									""
								],
								"type": "text/javascript"
							}
						},
						{
							"listen": "test",
							"script": {
								"id": "f590b07c-50f8-4600-826d-63354bb34a13",
								"exec": [
									"var body = JSON.parse(responseBody);",
									"",
									"pm.environment.set(\"ossOutputFileSignedUrl\", body[\"signedUrl\"]);"
								],
								"type": "text/javascript"
							}
						}
					],
					"request": {
						"method": "POST",
						"header": [
							{
								"key": "Content-Type",
								"value": "application/json"
							},
							{
								"key": "Authorization",
								"value": "Bearer {{dasApiToken}}"
							}
						],
						"body": {
							"mode": "raw",
							"raw": "{}"
						},
						"url": {
							"raw": "https://developer.api.autodesk.com/oss/v2/buckets/{{ossBucketKey}}/objects/{{ossOutputFileObjectKey}}/signed?access=readwrite",
							"protocol": "https",
							"host": [
								"developer",
								"api",
								"autodesk",
								"com"
							],
							"path": [
								"oss",
								"v2",
								"buckets",
								"{{ossBucketKey}}",
								"objects",
								"{{ossOutputFileObjectKey}}",
								"signed"
							],
							"query": [
								{
									"key": "access",
									"value": "readwrite"
								}
							]
						},
						"description": "[See documentation](https://forge.autodesk.com/en/docs/data/v2/reference/http/buckets-:bucketKey-objects-:objectName-signed-POST/)"
					},
					"response": []
				}
			],
			"event": [
				{
					"listen": "prerequest",
					"script": {
						"id": "3f22d8ff-3455-44b0-a821-b8729f2e30d6",
						"type": "text/javascript",
						"exec": [
							""
						]
					}
				},
				{
					"listen": "test",
					"script": {
						"id": "c61a0305-ea7a-4675-8d4e-2aef33758b7b",
						"type": "text/javascript",
						"exec": [
							""
						]
					}
				}
			],
			"protocolProfileBehavior": {}
		},
		{
			"name": "Task 6 - Submit a WorkItem",
			"item": [
				{
					"name": "Send WorkItem",
					"event": [
						{
							"listen": "test",
							"script": {
								"id": "5f687e42-5667-4e90-a7ad-1bb33fc0f786",
								"exec": [
									"var body = JSON.parse(responseBody);",
									"pm.environment.set(\"dasWorkItemId\", body[\"id\"]);"
								],
								"type": "text/javascript"
							}
						},
						{
							"listen": "prerequest",
							"script": {
								"id": "7c7be5e3-a6ba-40ae-9296-d196d4d8a904",
								"exec": [
									""
								],
								"type": "text/javascript"
							}
						}
					],
					"request": {
						"method": "POST",
						"header": [
							{
								"key": "Content-Type",
								"value": "application/json"
							},
							{
								"key": "Authorization",
								"value": "Bearer {{dasApiToken}}"
							}
						],
						"body": {
							"mode": "raw",
							"raw": "{\n\t\"activityId\": \"{{dasNickName}}.{{dasActivityName}}+{{dasActivityAlias}}\",\n\t\"arguments\": {\n\t\t\"InputDwg\": {\n            \"url\": \"{{ossDwgFileSignedUrl}}\",\n            \"verb\": \"get\"\n        },\n        \"result\": {\n        \t\"url\": \"{{ossOutputFileSignedUrl}}\",\n            \"verb\": \"put\"\n        }\n\t}\n}"
						},
						"url": {
							"raw": "https://developer.api.autodesk.com/da/us-east/v3/workitems",
							"protocol": "https",
							"host": [
								"developer",
								"api",
								"autodesk",
								"com"
							],
							"path": [
								"da",
								"us-east",
								"v3",
								"workitems"
							]
						},
						"description": "[See documentation](https://forge.autodesk.com/en/docs/design-automation/v3/reference/http/workitems-POST/)"
					},
					"response": []
				},
				{
					"name": "Check Status of the WorkItem",
					"request": {
						"method": "GET",
						"header": [
							{
								"key": "Content-Type",
								"value": "application/json"
							},
							{
								"key": "Authorization",
								"value": "Bearer {{dasApiToken}}"
							}
						],
						"url": {
							"raw": "https://developer.api.autodesk.com/da/us-east/v3/workitems/{{dasWorkItemId}}",
							"protocol": "https",
							"host": [
								"developer",
								"api",
								"autodesk",
								"com"
							],
							"path": [
								"da",
								"us-east",
								"v3",
								"workitems",
								"{{dasWorkItemId}}"
							]
						},
						"description": "[See documentation](https://forge.autodesk.com/en/docs/design-automation/v3/reference/http/workitems-id-GET/)"
					},
					"response": []
				}
			],
			"event": [
				{
					"listen": "prerequest",
					"script": {
						"id": "1132e67f-2739-47b3-914a-0f75a86224d1",
						"type": "text/javascript",
						"exec": [
							""
						]
					}
				},
				{
					"listen": "test",
					"script": {
						"id": "ce1fe857-f05c-4130-8e35-b2f9147e26d1",
						"type": "text/javascript",
						"exec": [
							""
						]
					}
				}
			],
			"protocolProfileBehavior": {}
		},
		{
			"name": "Task 7 - Download the Results ",
			"item": [
				{
					"name": "Download Output from OSS",
					"protocolProfileBehavior": {
						"disableBodyPruning": true
					},
					"request": {
						"method": "GET",
						"header": [
							{
								"key": "Content-Type",
								"value": "application/json"
							},
							{
								"key": "Authorization",
								"value": "Bearer {{dasApiToken}}"
							}
						],
						"body": {
							"mode": "raw",
							"raw": "{}"
						},
						"url": {
							"raw": "https://developer.api.autodesk.com/oss/v2/buckets/{{ossBucketKey}}/objects/{{ossOutputFileObjectKey}}",
							"protocol": "https",
							"host": [
								"developer",
								"api",
								"autodesk",
								"com"
							],
							"path": [
								"oss",
								"v2",
								"buckets",
								"{{ossBucketKey}}",
								"objects",
								"{{ossOutputFileObjectKey}}"
							]
						},
						"description": "[See documentation](https://forge.autodesk.com/en/docs/data/v2/reference/http/buckets-:bucketKey-objects-:objectName-GET/)"
					},
					"response": []
				}
			],
			"event": [
				{
					"listen": "prerequest",
					"script": {
						"id": "d77a1f77-f6f9-46ec-9146-cff573fa2f2c",
						"type": "text/javascript",
						"exec": [
							""
						]
					}
				},
				{
					"listen": "test",
					"script": {
						"id": "45f247a9-bfb1-464b-b5aa-ec2cbf9b3273",
						"type": "text/javascript",
						"exec": [
							""
						]
					}
				}
			],
			"protocolProfileBehavior": {}
		},
		{
			"name": "Extras",
			"item": [
				{
					"name": "Delete Forge App Data in Design Automation",
					"request": {
						"method": "DELETE",
						"header": [
							{
								"key": "Content-Type",
								"value": "application/json"
							},
							{
								"key": "Authorization",
								"value": "Bearer {{dasApiToken}}"
							}
						],
						"body": {
							"mode": "raw",
							"raw": ""
						},
						"url": {
							"raw": "https://developer.api.autodesk.com/da/us-east/v3/forgeapps/me",
							"protocol": "https",
							"host": [
								"developer",
								"api",
								"autodesk",
								"com"
							],
							"path": [
								"da",
								"us-east",
								"v3",
								"forgeapps",
								"me"
							]
						},
						"description": "[See documentation](https://forge.autodesk.com/en/docs/design-automation/v3/reference/http/forgeapps-id-DELETE/)"
					},
					"response": []
				},
				{
					"name": "Delete OSS Bucket",
					"event": [
						{
							"listen": "test",
							"script": {
								"id": "0ea5b8b5-1154-4350-bd8d-f59368b892ea",
								"exec": [
									""
								],
								"type": "text/javascript"
							}
						}
					],
					"request": {
						"method": "DELETE",
						"header": [
							{
								"key": "Content-Type",
								"value": "application/json"
							},
							{
								"key": "Authorization",
								"value": "Bearer {{dasApiToken}}"
							}
						],
						"body": {
							"mode": "raw",
							"raw": ""
						},
						"url": {
							"raw": "https://developer.api.autodesk.com/oss/v2/buckets/{{ossBucketKey}}",
							"protocol": "https",
							"host": [
								"developer",
								"api",
								"autodesk",
								"com"
							],
							"path": [
								"oss",
								"v2",
								"buckets",
								"{{ossBucketKey}}"
							]
						},
						"description": "[See documentation](https://forge.autodesk.com/en/docs/data/v2/reference/http/buckets-:bucketKey-DELETE/)"
					},
					"response": []
				},
				{
					"name": "List engines",
					"protocolProfileBehavior": {
						"disableBodyPruning": true
					},
					"request": {
						"method": "GET",
						"header": [
							{
								"key": "Authorization",
								"value": "Bearer {{dasApiToken}}",
								"type": "text"
							},
							{
								"key": "Content-Type",
								"name": "Content-Type",
								"value": "application/json",
								"type": "text"
							}
						],
						"body": {
							"mode": "raw",
							"raw": "",
							"options": {
								"raw": {
									"language": "json"
								}
							}
						},
						"url": {
							"raw": "https://developer.api.autodesk.com/da/us-east/v3/engines",
							"protocol": "https",
							"host": [
								"developer",
								"api",
								"autodesk",
								"com"
							],
							"path": [
								"da",
								"us-east",
								"v3",
								"engines"
							]
						},
						"description": "This request to the Design Automation API lists all the engines currently supported by Design Automation."
					},
					"response": []
				},
				{
					"name": "List Activities",
					"request": {
						"method": "GET",
						"header": [
							{
								"key": "Authorization",
								"value": "Bearer {{dasApiToken}}",
								"type": "text"
							}
						],
						"url": {
							"raw": "https://developer.api.autodesk.com/da/us-east/v3/activities",
							"protocol": "https",
							"host": [
								"developer",
								"api",
								"autodesk",
								"com"
							],
							"path": [
								"da",
								"us-east",
								"v3",
								"activities"
							]
						},
						"description": "[See documentation](https://forge.autodesk.com/en/docs/design-automation/v3/reference/http/activities-GET/)"
					},
					"response": []
				},
				{
					"name": "Delete Activity",
					"request": {
						"method": "DELETE",
						"header": [
							{
								"key": "Authorization",
								"type": "text",
								"value": "Bearer {{dasApiToken}}"
							}
						],
						"url": {
							"raw": "https://developer.api.autodesk.com/da/us-east/v3/activities/{{dasActivityName}}",
							"protocol": "https",
							"host": [
								"developer",
								"api",
								"autodesk",
								"com"
							],
							"path": [
								"da",
								"us-east",
								"v3",
								"activities",
								"{{dasActivityName}}"
							]
						},
						"description": "[See documentation](https://forge.autodesk.com/en/docs/design-automation/v3/reference/http/activities-GET/)"
					},
					"response": []
				},
				{
					"name": "List objects in a Bucket",
					"request": {
						"method": "GET",
						"header": [
							{
								"key": "Authorization",
								"value": "Bearer {{dasApiToken}}",
								"type": "text"
							}
						],
						"url": {
							"raw": "https://developer.api.autodesk.com/oss/v2/buckets/{{ossBucketKey}}/objects",
							"protocol": "https",
							"host": [
								"developer",
								"api",
								"autodesk",
								"com"
							],
							"path": [
								"oss",
								"v2",
								"buckets",
								"{{ossBucketKey}}",
								"objects"
							]
						},
						"description": "[See documentation](https://forge.autodesk.com/en/docs/data/v2/reference/http/buckets-:bucketKey-objects-GET/)"
					},
					"response": []
				},
				{
					"name": "List Buckets",
					"request": {
						"method": "GET",
						"header": [
							{
								"key": "Authorization",
								"value": "Bearer {{dasApiToken}}",
								"type": "text"
							}
						],
						"url": {
							"raw": "https://developer.api.autodesk.com/oss/v2/buckets",
							"protocol": "https",
							"host": [
								"developer",
								"api",
								"autodesk",
								"com"
							],
							"path": [
								"oss",
								"v2",
								"buckets"
							]
						},
						"description": "[See documentation](https://forge.autodesk.com/en/docs/data/v2/reference/http/buckets-GET/)"
					},
					"response": []
				},
				{
					"name": "Get Bucket Details",
					"request": {
						"method": "GET",
						"header": [
							{
								"key": "Authorization",
								"value": "Bearer {{dasApiToken}}",
								"type": "text"
							}
						],
						"url": {
							"raw": "https://developer.api.autodesk.com/oss/v2/buckets/{{ossBucketKey}}/details",
							"protocol": "https",
							"host": [
								"developer",
								"api",
								"autodesk",
								"com"
							],
							"path": [
								"oss",
								"v2",
								"buckets",
								"{{ossBucketKey}}",
								"details"
							]
						},
						"description": "[See documentation](https://forge.autodesk.com/en/docs/data/v2/reference/http/buckets-:bucketKey-details-GET/)"
					},
					"response": []
				}
			],
			"event": [
				{
					"listen": "prerequest",
					"script": {
						"id": "20d715f3-6887-4c89-8a03-55a79fcb4bba",
						"type": "text/javascript",
						"exec": [
							""
						]
					}
				},
				{
					"listen": "test",
					"script": {
						"id": "7ce34874-5d7d-4317-8808-a3715fb86712",
						"type": "text/javascript",
						"exec": [
							""
						]
					}
				}
			],
			"protocolProfileBehavior": {}
		}
	],
	"protocolProfileBehavior": {}
}